[{"name":" Concordia College (AL)","annual_tuition":"6826","reputation":"2","job_prospects":"3","financial_aid":"1","type":"Liberal Arts","location_size\n":"Large Town\n"},{"name":"Arkansas Baptist College (AK)","annual_tuition":"6400","reputation":"2","job_prospects":"3","financial_aid":"1","type":"Liberal Arts","location_size\n":"Small City\n"},{"name":"Pomona College (CA)","annual_tuition":"38807","reputation":"9","job_prospects":"3","financial_aid":"9","type":"Liberal Arts","location_size\n":"Large Town\n"},{"name":"San Diego Christian College (CA)","annual_tuition":"21610","reputation":"4","job_prospects":"3","financial_aid":"5","type":"Liberal Arts","location_size\n":"Small City\n"},{"name":"\"Uni. Of California","annual_tuition":" San Diego\"","reputation":"22669","job_prospects":"6","financial_aid":"3","type":"8","location_size\n":"University"},{"name":"Uni. Of Southern California","annual_tuition":"38570","reputation":"7","job_prospects":"3","financial_aid":"9","type":"University","location_size\n":"Very Large City\n"},{"name":"Stanford University (CA)","annual_tuition":"37380","reputation":"9","job_prospects":"3","financial_aid":"9","type":"University","location_size\n":"Small City\n"},{"name":"California Institute of Technology","annual_tuition":"31437","reputation":"9","job_prospects":"3","financial_aid":"9","type":"University","location_size\n":"Small City\n"},{"name":"Metropolitan State college of Denver (CO)","annual_tuition":"12343","reputation":"3","job_prospects":"3","financial_aid":"6","type":"Liberal Arts","location_size\n":"Very Large City\n"},{"name":"American Sentinel University (CO)","annual_tuition":"8850","reputation":"1","job_prospects":"3","financial_aid":"1","type":"University","location_size\n":"Very Large City\n"},{"name":"University of Denver (CO)","annual_tuition":"35604","reputation":"7","job_prospects":"3","financial_aid":"1","type":"University","location_size\n":"Very Large City\n"},{"name":"University of Connecticut (CT)","annual_tuition":"24528","reputation":"7","job_prospects":"3","financial_aid":"6","type":"University","location_size\n":"Large Town\n"},{"name":"Delaware State University (DE)","annual_tuition":"13742","reputation":"4","job_prospects":"3","financial_aid":"5","type":"University","location_size\n":"Large Town\n"},{"name":"University of Delaware (DE)","annual_tuition":"22240","reputation":"6","job_prospects":"3","financial_aid":"7","type":"University","location_size\n":"Large Town\n"},{"name":"Florida College (FL)","annual_tuition":"11400","reputation":"2","job_prospects":"3","financial_aid":"3","type":"Liberal Arts","location_size\n":"Large Town\n"},{"name":"Jones College (FL)","annual_tuition":"6600","reputation":"2","job_prospects":"3","financial_aid":"1","type":"Business and Education","location_size\n":"Very Large City\n"},{"name":"Florida Gulf Coast University (FL)","annual_tuition":"19450","reputation":"6","job_prospects":"3","financial_aid":"5","type":"University","location_size\n":"Small City\n"},{"name":"Florida Atlantic University (FL)","annual_tuition":"17532","reputation":"7","job_prospects":"3","financial_aid":"7","type":"University","location_size\n":"Small City\n"},{"name":"Warner University (FL)","annual_tuition":"15120","reputation":"5","job_prospects":"3","financial_aid":"1","type":"Liberal Arts","location_size\n":"Large Town\n"},{"name":"University of Miami (FL)","annual_tuition":"36962","reputation":"7","job_prospects":"3","financial_aid":"8","type":"University","location_size\n":"Small City\n"},{"name":"University of Florida (FL)","annual_tuition":"23744","reputation":"4","job_prospects":"3","financial_aid":"7","type":"University","location_size\n":"Small City\n"},{"name":"Atlanta Christian College (GA)","annual_tuition":"14450","reputation":"1","job_prospects":"3","financial_aid":"1","type":"Bible College","location_size\n":"Small City\n"},{"name":"Emmanual College (GA)","annual_tuition":"12880","reputation":"4","job_prospects":"3","financial_aid":"7","type":"Liberal Arts","location_size\n":"Rural Community\n"},{"name":"Augusta State University (GA)","annual_tuition":"12408","reputation":"3","job_prospects":"3","financial_aid":"1","type":"Liberal Arts","location_size\n":"Small City\n"},{"name":"University of Georgia (GA) ","annual_tuition":"24280","reputation":"7","job_prospects":"3","financial_aid":"8","type":"University","location_size\n":"Small City\n"},{"name":"Georgia Institute of Technology (GA)","annual_tuition":"24480","reputation":"8","job_prospects":"3","financial_aid":"7","type":"University","location_size\n":"Very Large City\n"},{"name":"University of Guam (GU)","annual_tuition":"15820","reputation":"2","job_prospects":"3","financial_aid":"1","type":"University","location_size\n":"Large Town\n"},{"name":"Hawaii Pacific University (HI)","annual_tuition":"14860","reputation":"6","job_prospects":"3","financial_aid":"8","type":"Liberal Arts","location_size\n":"Large City\n"},{"name":"Brigham Young University (HI)","annual_tuition":"4330","reputation":"5","job_prospects":"3","financial_aid":"7","type":"Liberal Arts","location_size\n":"Small Town\n"},{"name":"Ashford University (IA)","annual_tuition":"15340","reputation":"3","job_prospects":"3","financial_aid":"8","type":"Proprietary","location_size\n":"large town\n"},{"name":"Simpson College (IA)","annual_tuition":"25366","reputation":"7","job_prospects":"3","financial_aid":"9","type":"Liberal Arts","location_size\n":"Large Town\n"},{"name":"The University of Iowa (IA)","annual_tuition":"22424","reputation":"8","job_prospects":"3","financial_aid":"1","type":"University","location_size\n":"Small City\n"},{"name":"The College of Idaho (ID)","annual_tuition":"20600","reputation":"8","job_prospects":"3","financial_aid":"9","type":"Liberal Arts","location_size\n":"Large Town\n"},{"name":"University of Idaho (ID)","annual_tuition":"10080","reputation":"7","job_prospects":"3","financial_aid":"7","type":"University","location_size\n":"Large Town\n"},{"name":"Chicago State University (IL)","annual_tuition":"13650","reputation":"4","job_prospects":"3","financial_aid":"1","type":"University","location_size\n":"Very Large City\n"},{"name":"Quincy University (IL)","annual_tuition":"21300","reputation":"6","job_prospects":"3","financial_aid":"8","type":"Liberal Arts","location_size\n":"Large Town\n"},{"name":"Louisiana College (LA)","annual_tuition":"11100","reputation":"5","job_prospects":"3","financial_aid":"1","type":"Liberal Arts","location_size\n":"Small City\n"},{"name":"University of New Orleans (LA)","annual_tuition":"11860","reputation":"5","job_prospects":"3","financial_aid":"6","type":"University","location_size\n":"Very Large City\n"},{"name":"Griggs University (MD)","annual_tuition":"7800","reputation":"1","job_prospects":"3","financial_aid":"1","type":"Liberal Arts","location_size\n":"small city\n"},{"name":"\"University of Maryland","annual_tuition":" Baltimore County (MD)\"","reputation":"15825","job_prospects":"8","financial_aid":"3","type":"6","location_size\n":"University"},{"name":"Adrian College (MI)","annual_tuition":"24140","reputation":"7","job_prospects":"3","financial_aid":"10","type":"Liberal Arts","location_size\n":"Large Town\n"},{"name":"\"University of Michigan","annual_tuition":" Flint (MI)\"","reputation":"15413","job_prospects":"6","financial_aid":"3","type":"7","location_size\n":"University"},{"name":"Michigan State University (MI)","annual_tuition":"26873","reputation":"7","job_prospects":"3","financial_aid":"4","type":"University","location_size\n":"Small City\n"},{"name":"Mississippi College (MS)","annual_tuition":"12900","reputation":"6","job_prospects":"3","financial_aid":"7","type":"University","location_size\n":"Large City\n"},{"name":"Elon University (NC)","annual_tuition":"25159","reputation":"6","job_prospects":"3","financial_aid":"7","type":"Liberal Arts","location_size\n":"Large Town\n"},{"name":"North Carolina State University (NC)","annual_tuition":"16438","reputation":"7","job_prospects":"3","financial_aid":"8","type":"University","location_size\n":"Large City\n"},{"name":"University of North Carolina at Chapel Hill (NC)","annual_tuition":"21753","reputation":"8","job_prospects":"3","financial_aid":"9","type":"University","location_size\n":"Large Town\n"},{"name":"University of North Carolina at Chalotte (NC)","annual_tuition":"13128","reputation":"7","job_prospects":"3","financial_aid":"7","type":"University","location_size\n":"Very Large City\n"},{"name":"Southern Virginia University (VA)","annual_tuition":"17000","reputation":"3","job_prospects":"3","financial_aid":"5","type":"Liberal Arts","location_size\n":"Small Town\n"},{"name":"University of Richmond (VA)","annual_tuition":"41610","reputation":"8","job_prospects":"3","financial_aid":"10","type":"Liberal Arts","location_size\n":"Small City"}]
